material_color_palette/__init__.py
material_color_palette/py.typed
material_color_palette-1.1.0.post1.dist-info/METADATA
material_color_palette-1.1.0.post1.dist-info/WHEEL
material_color_palette-1.1.0.post1.dist-info/licenses/LICENSE
material_color_palette-1.1.0.post1.dist-info/RECORD
