Metadata-Version: 2.4
Name: material-color-palette
Version: 1.1.0.post1
Summary: Google's original 2014 Material Design color palettes as a Python library
Project-URL: Source, https://github.com/elliot-100/material-color-palette
Project-URL: Changelog, https://github.com/elliot-100/material-color-palette/blob/main/CHANGELOG.md
Project-URL: Issues, https://github.com/elliot-100/material-color-palette/issues
Author-email: elliot-100 <3186037+elliot-100@users.noreply.github.com>
License-Expression: MIT
License-File: LICENSE
Keywords: color,colors,colour,colours,design,google,material,palette,palettes
Classifier: Development Status :: 5 - Production/Stable
Classifier: Intended Audience :: Developers
Classifier: Operating System :: OS Independent
Classifier: Programming Language :: Python :: 3
Classifier: Programming Language :: Python :: 3.10
Classifier: Programming Language :: Python :: 3.11
Classifier: Programming Language :: Python :: 3.12
Classifier: Programming Language :: Python :: 3.13
Classifier: Programming Language :: Python :: 3.14
Classifier: Typing :: Typed
Requires-Python: >=3.10
